ptm_ocr/__init__.py
ptm_ocr/cli.py
ptm_ocr/core.py
ptm_ocr/py.typed
ptm_ocr-0.1.1.dist-info/METADATA
ptm_ocr-0.1.1.dist-info/WHEEL
ptm_ocr-0.1.1.dist-info/entry_points.txt
ptm_ocr-0.1.1.dist-info/licenses/LICENSE
ptm_ocr-0.1.1.dist-info/RECORD
