Metadata-Version: 2.4
Name: ptm-ocr
Version: 0.1.1
Summary: Batch OCR Processing for Thai Documents using Typhoon OCR API
Project-URL: Homepage, https://github.com/nectec-ptm/ptm-ocr
Project-URL: Repository, https://github.com/nectec-ptm/ptm-ocr
Author: NECTEC ThaiLLM Team
License: MIT
License-File: LICENSE
Keywords: batch-processing,ocr,pdf,thai,typhoon
Classifier: Development Status :: 4 - Beta
Classifier: Intended Audience :: Developers
Classifier: License :: OSI Approved :: MIT License
Classifier: Programming Language :: Python :: 3
Classifier: Programming Language :: Python :: 3.9
Classifier: Programming Language :: Python :: 3.10
Classifier: Programming Language :: Python :: 3.11
Classifier: Programming Language :: Python :: 3.12
Classifier: Topic :: Text Processing :: General
Requires-Python: >=3.9
Requires-Dist: openai>=1.0.0
Requires-Dist: pillow
Requires-Dist: pymupdf
Requires-Dist: python-dotenv
Requires-Dist: tqdm
Requires-Dist: typhoon-ocr
Provides-Extra: dev
Requires-Dist: build; extra == 'dev'
Requires-Dist: pytest; extra == 'dev'
Requires-Dist: twine; extra == 'dev'
